GAVS/GAVS.py
GAVS/HELP.py
GAVS/XPM.py
GAVS/XVG.py
GAVS/__init__.py
GAVS-1.0.0.dist-info/LICENSE
GAVS-1.0.0.dist-info/METADATA
GAVS-1.0.0.dist-info/WHEEL
GAVS-1.0.0.dist-info/entry_points.txt
GAVS-1.0.0.dist-info/top_level.txt
GAVS-1.0.0.dist-info/RECORD
