Metadata-Version: 2.1
Name: GAVS
Version: 1.0.0
Summary: A tool for GROMACS results analysis and visualization
Home-page: UNKNOWN
Author: YinleiHan
Author-email: 
License: UNKNOWN
Platform: cross-platform
Classifier: Development Status :: 5 - Production/Stable
Classifier: License :: OSI Approved :: GNU General Public License v2 (GPLv2)
Classifier: Programming Language :: Python
Classifier: Programming Language :: Python :: 3
Classifier: Topic :: Scientific/Engineering :: Bio-Informatics
Classifier: Topic :: Scientific/Engineering :: Chemistry
Classifier: Intended Audience :: Science/Research
Requires-Dist: matplotlib
Requires-Dist: numpy
Requires-Dist: scipy
Requires-Dist: argparse
Provides-Extra: test
Requires-Dist: pytest ; extra == 'test'
Requires-Dist: coverage ; extra == 'test'
Requires-Dist: pytest-cov ; extra == 'test'
Requires-Dist: collective.checkdocs ; extra == 'test'
Requires-Dist: pygments ; extra == 'test'
Requires-Dist: matplotlib ; extra == 'test'
Requires-Dist: numpy ; extra == 'test'
Requires-Dist: scipy ; extra == 'test'
Requires-Dist: argparse ; extra == 'test'
